{
  "updated": "2026-06-12T08:24:50.142782+09:00",
  "scorers": [
    {
      "player_id": 39237,
      "player_name": "Julián Quiñones",
      "nationality": "Colombia",
      "team_id": 769,
      "team_ja": "メキシコ",
      "team_flag": "🇲🇽",
      "goals": 1,
      "assists": null,
      "playedMatches": 1
    },
    {
      "player_id": 3305,
      "player_name": "Raúl Jiménez",
      "nationality": "Mexico",
      "team_id": 769,
      "team_ja": "メキシコ",
      "team_flag": "🇲🇽",
      "goals": 1,
      "assists": null,
      "playedMatches": 1
    }
  ]
}